LICENSE.txt
MANIFEST.in
dbgpClient.py
setup.py
bin/dbg.py
bin/pydbgp.py
bin/pydbgpd.py
bin/pydbgpproxy.py
bin/pydbgpshell.py
dbgp/__init__.py
dbgp/_client.c
dbgp/_pyclient.py
dbgp/client.py
dbgp/common.py
dbgp/listcmd.py
dbgp/server.py
dbgp/serverBase.py
dbgp.egg-info/PKG-INFO
dbgp.egg-info/SOURCES.txt
dbgp.egg-info/dependency_links.txt
dbgp.egg-info/top_level.txt
dbgp/_logging/__init__.py
dbgp/_logging/config.py
dbgp/_logging/handlers.py
symbian/dbgp.app
symbian/dbgp.pkg
symbian/dbgp.rsc
symbian/debug.py
symbian/serial_tcp_redirect.py
symbian/lib/Queue.py
symbian/lib/cmd.py
symbian/lib/getopt.py
symbian/lib/ihooks.py
symbian/lib/logging.py
symbian/lib/threading.py