Metadata-Version: 1.0
Name: dbgp
Version: 1.1
Summary: a python debug server that is complient with DBGP
Home-page: http://jabapyth.github.com/pydbgp/
Author: Jared Forsyth
Author-email: jared@jaredforsyth.com
License: UNKNOWN
Platform: UNKNOWN
